geezswitch/__init__.py
geezswitch/detector.py
geezswitch/detector_factory.py
geezswitch/lang_detect_exception.py
geezswitch/language.py
geezswitch/profiles/af
geezswitch/profiles/amh
geezswitch/profiles/ar
geezswitch/profiles/bg
geezswitch/profiles/bn
geezswitch/profiles/byn
geezswitch/profiles/ca
geezswitch/profiles/cs
geezswitch/profiles/cy
geezswitch/profiles/da
geezswitch/profiles/de
geezswitch/profiles/el
geezswitch/profiles/en
geezswitch/profiles/es
geezswitch/profiles/et
geezswitch/profiles/fa
geezswitch/profiles/fi
geezswitch/profiles/fr
geezswitch/profiles/gez
geezswitch/profiles/gu
geezswitch/profiles/he
geezswitch/profiles/hi
geezswitch/profiles/hr
geezswitch/profiles/hu
geezswitch/profiles/id
geezswitch/profiles/it
geezswitch/profiles/ja
geezswitch/profiles/kn
geezswitch/profiles/ko
geezswitch/profiles/lt
geezswitch/profiles/lv
geezswitch/profiles/mk
geezswitch/profiles/ml
geezswitch/profiles/mr
geezswitch/profiles/ne
geezswitch/profiles/nl
geezswitch/profiles/no
geezswitch/profiles/pa
geezswitch/profiles/pl
geezswitch/profiles/pt
geezswitch/profiles/ro
geezswitch/profiles/ru
geezswitch/profiles/sk
geezswitch/profiles/sl
geezswitch/profiles/so
geezswitch/profiles/sq
geezswitch/profiles/sv
geezswitch/profiles/sw
geezswitch/profiles/ta
geezswitch/profiles/te
geezswitch/profiles/th
geezswitch/profiles/tig
geezswitch/profiles/tir
geezswitch/profiles/tl
geezswitch/profiles/tr
geezswitch/profiles/uk
geezswitch/profiles/ur
geezswitch/profiles/vi
geezswitch/profiles/zh-cn
geezswitch/profiles/zh-tw
geezswitch/tests/__init__.py
geezswitch/tests/test_detector.py
geezswitch/tests/test_language.py
geezswitch/utils/__init__.py
geezswitch/utils/lang_profile.py
geezswitch/utils/messages.properties
geezswitch/utils/messages.py
geezswitch/utils/ngram.py
geezswitch/utils/unicode_block.py
geezswitch-1.0.1.dist-info/LICENSE
geezswitch-1.0.1.dist-info/METADATA
geezswitch-1.0.1.dist-info/NOTICE
geezswitch-1.0.1.dist-info/WHEEL
geezswitch-1.0.1.dist-info/top_level.txt
geezswitch-1.0.1.dist-info/RECORD
