Metadata-Version: 2.1
Name: geezswitch
Version: 1.0.1
Summary: Language Identification library.
Home-page: https://github.com/fgaim/geezswitch
Author: Fitsum Gaim
Author-email: fitsum@geezlab.com
License: Apache 2.0
Keywords: language identification
Platform: UNKNOWN
Classifier: Development Status :: 5 - Production/Stable
Classifier: Intended Audience :: Developers
Classifier: License :: OSI Approved :: Apache Software License
Classifier: Operating System :: OS Independent
Classifier: Programming Language :: Python :: 2
Classifier: Programming Language :: Python :: 2.7
Classifier: Programming Language :: Python :: 3
Classifier: Programming Language :: Python :: 3.4
Classifier: Programming Language :: Python :: 3.5
Classifier: Programming Language :: Python :: 3.6
Classifier: Programming Language :: Python :: 3.7
Classifier: Programming Language :: Python :: 3.8
Requires-Dist: six
